dify_client/__init__.py
dify_client/_clientx.py
dify_client/errors.py
dify_client/models/__init__.py
dify_client/models/base.py
dify_client/models/chat.py
dify_client/models/completion.py
dify_client/models/converstation.py
dify_client/models/dataset.py
dify_client/models/feedback.py
dify_client/models/file.py
dify_client/models/message.py
dify_client/models/stream.py
dify_client/models/workflow.py
dify_client/tests/test_clientx.py
dify_client/tests/utils/test_common.py
dify_client/utils/__init__.py
dify_client/utils/_common.py
dify_api_client-0.0.15.dist-info/METADATA
dify_api_client-0.0.15.dist-info/WHEEL
dify_api_client-0.0.15.dist-info/entry_points.txt
dify_api_client-0.0.15.dist-info/licenses/LICENSE.md
dify_api_client-0.0.15.dist-info/RECORD
