Metadata-Version: 2.4
Name: dify-api-client
Version: 0.0.15
Summary: dify-api-client - A package for interacting with the Dify Service-API
Project-URL: Homepage, https://github.com/lucas-castalk/dify-api-client
Project-URL: Source, https://github.com/lucas-castalk/dify-api-client
Author-email: lucas <lucas@castalk.com>
License: MIT License
License-File: LICENSE.md
Keywords: dify-api,dify-client
Classifier: Operating System :: OS Independent
Classifier: Programming Language :: Python :: 3
Requires-Python: >=3.10
Requires-Dist: dotenv>=0.9.9
Requires-Dist: httpx-sse>=0.4.0
Requires-Dist: httpx>=0.28.1
Requires-Dist: pydantic>=2.10.4
Provides-Extra: dev
Requires-Dist: hatch>=1.14.1; extra == 'dev'
Requires-Dist: pre-commit; extra == 'dev'
Requires-Dist: pylint; extra == 'dev'
Requires-Dist: pytest; extra == 'dev'
Requires-Dist: ruff>=0.11.13; extra == 'dev'
Requires-Dist: twine>=6.1.0; extra == 'dev'
